behavioral_signals_swagger_client_3/__init__.py
behavioral_signals_swagger_client_3/api_client.py
behavioral_signals_swagger_client_3/configuration.py
behavioral_signals_swagger_client_3/rest.py
behavioral_signals_swagger_client_3/api/__init__.py
behavioral_signals_swagger_client_3/api/call_processing_api.py
behavioral_signals_swagger_client_3/api/default_api.py
behavioral_signals_swagger_client_3/api/update_processes_status_e_g_to_abort_processing_api.py
behavioral_signals_swagger_client_3/models/__init__.py
behavioral_signals_swagger_client_3/models/array_of_processes.py
behavioral_signals_swagger_client_3/models/authorized.py
behavioral_signals_swagger_client_3/models/body.py
behavioral_signals_swagger_client_3/models/callflow_events.py
behavioral_signals_swagger_client_3/models/callflow_events_inner.py
behavioral_signals_swagger_client_3/models/client.py
behavioral_signals_swagger_client_3/models/clients.py
behavioral_signals_swagger_client_3/models/error_model.py
behavioral_signals_swagger_client_3/models/generic_response.py
behavioral_signals_swagger_client_3/models/input_feedback.py
behavioral_signals_swagger_client_3/models/pagination_response.py
behavioral_signals_swagger_client_3/models/process.py
behavioral_signals_swagger_client_3/models/process_stats.py
behavioral_signals_swagger_client_3/models/process_updated_status.py
behavioral_signals_swagger_client_3/models/processes_update.py
behavioral_signals_swagger_client_3/models/processes_updated_status.py
behavioral_signals_swagger_client_3/models/request_process_body.py
behavioral_signals_swagger_client_3/models/request_task.py
behavioral_signals_swagger_client_3/models/request_task_options.py
behavioral_signals_swagger_client_3/models/request_task_options_data.py
behavioral_signals_swagger_client_3/models/request_tasks.py
behavioral_signals_swagger_client_3/models/response_feedback.py
behavioral_signals_swagger_client_3/models/result_json.py
behavioral_signals_swagger_client_3-3.11.1.dist-info/METADATA
behavioral_signals_swagger_client_3-3.11.1.dist-info/WHEEL
behavioral_signals_swagger_client_3-3.11.1.dist-info/top_level.txt
behavioral_signals_swagger_client_3-3.11.1.dist-info/RECORD
